plexdevices/__init__.py
plexdevices/api.py
plexdevices/compat.py
plexdevices/device.py
plexdevices/exceptions.py
plexdevices/factory.py
plexdevices/hubs.py
plexdevices/media.py
plexdevices/remote.py
plexdevices/session.py
plexdevices/types.py
plexdevices/utils.py
plexdevices-0.4.1.dist-info/DESCRIPTION.rst
plexdevices-0.4.1.dist-info/METADATA
plexdevices-0.4.1.dist-info/RECORD
plexdevices-0.4.1.dist-info/WHEEL
plexdevices-0.4.1.dist-info/metadata.json
plexdevices-0.4.1.dist-info/top_level.txt
