Metadata-Version: 2.0
Name: plexdevices
Version: 0.4.1
Summary: Python module for Plex devices.
Home-page: https://github.com/coryo/plexdevices
Author: Cory Parsons
Author-email: parsons.cory@gmail.com
License: Apache 2.0
Requires-Dist: requests
